Metadata-Version: 2.1
Name: floralatin-hubble-sdk9
Version: 1.0.2
Summary: SDK for Hubble API at Jina AI.
Home-page: https://github.com/jina-ai/hubble-client-python/
Download-URL: https://github.com/jina-ai/hubble-client-python/tags
Author: Jina AI
Author-email: hello@jina.ai
License: Proprietary
Project-URL: Source, https://github.com/jina-ai/hubble-client-python/
Project-URL: Tracker, https://github.com/jina-ai/hubble-client-python/issues
Keywords: jina neural-search neural-network deep-learning pretraining fine-tuning pretrained-models triplet-loss metric-learning siamese-network few-shot-learning
Classifier: Development Status :: 3 - Alpha
Classifier: Intended Audience :: Developers
Classifier: Intended Audience :: Education
Classifier: Intended Audience :: Science/Research
Classifier: Programming Language :: Python :: 3.7
Classifier: Programming Language :: Python :: 3.8
Classifier: Programming Language :: Python :: 3.9
Classifier: Programming Language :: Python :: 3.10
Classifier: Environment :: Console
Classifier: Operating System :: OS Independent
Classifier: Topic :: Scientific/Engineering :: Artificial Intelligence
Requires-Python: >=3.7.0
Requires-Dist: requests
Requires-Dist: aiohttp
Requires-Dist: rich
Requires-Dist: importlib-metadata
Requires-Dist: filelock
Requires-Dist: pathspec
Requires-Dist: cryptography
Requires-Dist: docker
Requires-Dist: pyyaml
Provides-Extra: full
Requires-Dist: black (==22.3.0) ; extra == 'full'
Requires-Dist: flake8 (==4.0.1) ; extra == 'full'
Requires-Dist: isort (==5.10.1) ; extra == 'full'
Requires-Dist: pytest (==7.0.0) ; extra == 'full'
Requires-Dist: pytest-asyncio (==0.19.0) ; extra == 'full'
Requires-Dist: pytest-cov (==3.0.0) ; extra == 'full'
Requires-Dist: pytest-mock (==3.7.0) ; extra == 'full'
Requires-Dist: mock (==4.0.3) ; extra == 'full'
Requires-Dist: grayskull ; extra == 'full'
Requires-Dist: requests ; extra == 'full'
Requires-Dist: aiohttp ; extra == 'full'
Requires-Dist: rich ; extra == 'full'
Requires-Dist: importlib-metadata ; extra == 'full'
Requires-Dist: filelock ; extra == 'full'
Requires-Dist: pathspec ; extra == 'full'
Requires-Dist: cryptography ; extra == 'full'
Requires-Dist: docker ; extra == 'full'
Requires-Dist: pyyaml ; extra == 'full'
